csvEmail.py
csvEmail-0.1.dist-info/LICENSE.txt
csvEmail-0.1.dist-info/METADATA
csvEmail-0.1.dist-info/WHEEL
csvEmail-0.1.dist-info/top_level.txt
csvEmail-0.1.dist-info/RECORD
