Metadata-Version: 2.1
Name: csvEmail
Version: 0.1
Summary: Script for sending mass emails based on the contents of a CSV file, where each row includes an email address and message details. Details from the row are filled into a template file to compose the emails. Does a dry run by default.
Home-page: https://cs.wellesley.edu/~pmwh/csvEmail/docs/csvEmail.html
Author: Peter Mawhorter
Author-email: pmawhort@wellesley.edu
License: BSD 3-Clause License
Classifier: Programming Language :: Python :: 3 :: Only
Classifier: Development Status :: 3 - Alpha
Classifier: Intended Audience :: Education
Classifier: Intended Audience :: Developers
Classifier: License :: OSI Approved :: BSD License
Classifier: Operating System :: OS Independent
Classifier: Natural Language :: English
Classifier: Topic :: Communications :: Email
Requires-Python: >=3.6
License-File: LICENSE.txt
Provides-Extra: test
Requires-Dist: pytest ; extra == 'test'
